Potoo.egg-info/PKG-INFO
Potoo.egg-info/SOURCES.txt
Potoo.egg-info/dependency_links.txt
Potoo.egg-info/entry_points.txt
Potoo.egg-info/requires.txt
Potoo.egg-info/top_level.txt
potoo-0.1.2.dist-info/METADATA
potoo-0.1.2.dist-info/WHEEL
potoo-0.1.2.dist-info/entry_points.txt
potoo-0.1.2.dist-info/licenses/LICENSE
potoo/__init__.py
potoo/__main__.py
potoo/app.py
potoo/cli.py
potoo/export.py
potoo/parse.py
potoo/potoo.css
potoo/types.py
potoo-0.1.2.dist-info/RECORD
