Metadata-Version: 2.1
Name: Potoo
Version: 0.1.2
Summary: Markdown presentation tool build on top of textual
Author-Email: Gilbus <gilbus@tinkershell.eu>
License: GPLv3+
Classifier: Environment :: Console
Classifier: License :: OSI Approved :: GNU General Public License v3 or later (GPLv3+)
Classifier: Programming Language :: Python :: 3
Classifier: Programming Language :: Python :: 3.10
Classifier: Programming Language :: Python :: 3.11
Classifier: Topic :: Text Processing :: Markup :: Markdown
Project-URL: Repository, https://gitlab.com/gilbus/potoo
Requires-Python: >=3.10
Requires-Dist: textual<0.31.0
Requires-Dist: pyyaml>=6.0
Requires-Dist: watchfiles>=0.19.0
Requires-Dist: textual-dev>=1.0.1; extra == "dev"
Requires-Dist: ruff>=0.0.278; extra == "dev"
Requires-Dist: mypy>=1.4.1; extra == "dev"
Requires-Dist: types-PyYAML>=6.0.12.10; extra == "dev"
Provides-Extra: dev
